flake8_encodings-0.5.0.dist-info/entry_points.txt
flake8_encodings-0.5.0.dist-info/top_level.txt
flake8_encodings-0.5.0.dist-info/METADATA
flake8_encodings-0.5.0.dist-info/WHEEL
flake8_encodings-0.5.0.dist-info/LICENSE
flake8_encodings/__init__.py
flake8_encodings/py.typed
flake8_encodings-0.5.0.dist-info/RECORD
