Metadata-Version: 2.1
Name: flake8-encodings
Version: 0.5.0
Summary: A Flake8 plugin to identify incorrect use of encodings.
Author-email: Dominic Davis-Foster <dominic@davis-foster.co.uk>
License: MIT
Keywords: encodings,flake8,pep597,unicode
Home-page: https://github.com/python-formate/flake8-encodings
Project-URL: Issue Tracker, https://github.com/python-formate/flake8-encodings/issues
Project-URL: Source Code, https://github.com/python-formate/flake8-encodings
Project-URL: Documentation, https://flake8-encodings.readthedocs.io/en/latest
Platform: Windows
Platform: macOS
Platform: Linux
Classifier: Development Status :: 4 - Beta
Classifier: Framework :: Flake8
Classifier: Intended Audience :: Developers
Classifier: License :: OSI Approved :: MIT License
Classifier: Operating System :: OS Independent
Classifier: Programming Language :: Python
Classifier: Programming Language :: Python :: 3 :: Only
Classifier: Programming Language :: Python :: 3.6
Classifier: Programming Language :: Python :: 3.7
Classifier: Programming Language :: Python :: 3.8
Classifier: Programming Language :: Python :: 3.9
Classifier: Programming Language :: Python :: 3.10
Classifier: Programming Language :: Python :: Implementation :: CPython
Classifier: Programming Language :: Python :: Implementation :: PyPy
Classifier: Topic :: Utilities
Classifier: Typing :: Typed
Requires-Python: >=3.6
Requires-Dist: astatine>=0.3.1
Requires-Dist: domdf-python-tools>=2.8.1
Requires-Dist: flake8>=3.8.4
Requires-Dist: flake8-helper>=0.1.1
Provides-Extra: classes
Requires-Dist: jedi>=0.18.0; extra == 'classes'
Provides-Extra: all
Requires-Dist: jedi>=0.18.0; extra == 'all'
